setup.py
mongodb_beaker/__init__.py
mongodb_beaker.egg-info/PKG-INFO
mongodb_beaker.egg-info/SOURCES.txt
mongodb_beaker.egg-info/dependency_links.txt
mongodb_beaker.egg-info/entry_points.txt
mongodb_beaker.egg-info/requires.txt
mongodb_beaker.egg-info/top_level.txt
mongodb_beaker.egg-info/zip-safe
tests/__init__.py
tests/test_default.py
tests/test_nopickle.py
tests/test_sparse.py