Metadata-Version: 1.1
Name: mongodb-beaker
Version: 0.5
Summary: Beaker backend to write sessions and caches to a MongoDB schemaless database.
Home-page: http://github.com/bwmcadams/mongodb_beaker/
Author: Brendan W. McAdams
Author-email: bwmcadams@gmail.com
License: New BSD License
Keywords: mongo mongodb beaker cache session
Platform: UNKNOWN
Classifier: Development Status :: 4 - Beta
Classifier: Environment :: Other Environment
Classifier: Environment :: Web Environment
Classifier: Intended Audience :: Developers
Classifier: License :: OSI Approved :: BSD License
Classifier: Operating System :: OS Independent
Classifier: Programming Language :: Python
Classifier: Topic :: Database
Classifier: Topic :: Utilities
Classifier: Topic :: Software Development :: Libraries :: Python Modules
Requires: pymongo
Requires: beaker
